{"@context":"https://iiif.io/api/presentation/3/context.json","id":"https://markpbaggett.github.io/beauford-delaney/api/facet/subject/finance-personal.json","type":"Collection","label":{"none":["Finance, Personal"]},"items":[{"id":"https://digital.lib.utk.edu/assemble/manifest/delaney/1930","type":"Manifest","label":{"en":["Beauford Delaney sketchbook, book 40"]},"thumbnail":[{"id":"https://digital.lib.utk.edu/collections/islandora/object/delaney%3A1930/datastream/TN","width":200,"height":200,"type":"Image","format":"image/jpeg"}],"homepage":[{"id":"https://markpbaggett.github.io/beauford-delaney/works/beauford-delaney-sketchbook-book-40","type":"Text","label":{"en":["Beauford Delaney sketchbook, book 40"]}}]},{"id":"https://digital.lib.utk.edu/assemble/manifest/delaney/1928","type":"Manifest","label":{"en":["Beauford Delaney notebook, book 46"]},"thumbnail":[{"id":"https://digital.lib.utk.edu/collections/islandora/object/delaney%3A1928/datastream/TN","width":200,"height":200,"type":"Image","format":"image/jpeg"}],"homepage":[{"id":"https://markpbaggett.github.io/beauford-delaney/works/beauford-delaney-notebook-book-46","type":"Text","label":{"en":["Beauford Delaney notebook, book 46"]}}]}],"partOf":[{"id":"https://markpbaggett.github.io/beauford-delaney/api/facet/subject.json","type":"Collection"}],"summary":{"none":["Subject"]},"homepage":[{"id":"https://markpbaggett.github.io/beauford-delaney/search?subject=finance-personal","type":"Text","label":{"none":["Finance, Personal"]}}]}